aegis/__init__.py
aegis/__main__.py
aegis/_bin/aegis_prover
aegis/_bin/macos/aegis_prover-real
aegis/_version.py
aegis/aegis_client.cpython-310-darwin.so
aegis/aegisprove.py
aegis/bloom.py
aegis/cli.py
aegis/cli_bloom.py
aegis/client.py
aegis/licensing.py
aegis/models.py
aegis_client-0.2.0.dist-info/METADATA
aegis_client-0.2.0.dist-info/WHEEL
aegis_client-0.2.0.dist-info/entry_points.txt
aegis_client-0.2.0.dist-info/RECORD
