Metadata-Version: 2.4
Name: aegis-client
Version: 0.2.0
Classifier: Development Status :: 4 - Beta
Classifier: Intended Audience :: Developers
Classifier: Intended Audience :: Legal Industry
Classifier: License :: OSI Approved :: Apache Software License
Classifier: Operating System :: OS Independent
Classifier: Programming Language :: Python :: 3
Classifier: Programming Language :: Python :: 3.8
Classifier: Programming Language :: Python :: 3.9
Classifier: Programming Language :: Python :: 3.10
Classifier: Programming Language :: Python :: 3.11
Classifier: Programming Language :: Python :: 3.12
Classifier: Programming Language :: Rust
Classifier: Topic :: Software Development :: Libraries :: Python Modules
Classifier: Topic :: Scientific/Engineering :: Artificial Intelligence
Classifier: Topic :: Office/Business
Classifier: Topic :: Security :: Cryptography
Requires-Dist: pydantic>=2.0.0
Requires-Dist: typing-extensions>=4.0.0
Requires-Dist: requests>=2.28.0
Requires-Dist: bitarray>=2.8.0
Summary: Copyright compliance for AI training via dual-licensed bloom filters
Keywords: copyright,ai-compliance,bloom-filter,ai-training,legal-tech,dual-licensing
Author-email: Aegis Testing Technologies LLC <support@aegisprove.com>
License: Apache-2.0
Requires-Python: >=3.8
Project-URL: homepage, https://aegisprove.com
Project-URL: repository, https://github.com/Aegis-Testing-Technologies/aegis-techspike
Project-URL: documentation, https://github.com/Aegis-Testing-Technologies/aegis-techspike/tree/main/docs
Project-URL: Bug Tracker, https://github.com/Aegis-Testing-Technologies/aegis-techspike/issues
